{
  "forge_marker": 1,
  "defaults": {
    "textures": {
      "end": "radioactiveblocks:blocks/log_big_oak_top",
      "side": "radioactiveblocks:blocks/log_big_oak"
    }
  },
  "variants": {
    "axis": {
      "y": { "model": "radioactiveblocks:radioactive_dark_oak_log" },
      "z": { "model": "radioactiveblocks:radioactive_dark_oak_log", "x": 90 },
      "x": { "model": "radioactiveblocks:radioactive_dark_oak_log", "x": 90, "y": 90 },
      "none": { "model": "radioactiveblocks:radioactive_dark_oak_bark" }
    }
  }
}
